Metadata-Version: 2.4
Name: awslabs.qbusiness-anonymous-mcp-server
Version: 0.1.0
Summary: An MCP server for awslaus.quusiness anonymous mcp server operations and management
Author-email: sicksec <sicksec@wearehackerone.com>
License: MIT
Project-URL: Homepage, https://github.com/sicks3c/awslabs.qbusiness-anonymous-mcp-server
Project-URL: Repository, https://github.com/sicks3c/awslabs.qbusiness-anonymous-mcp-server
Classifier: Development Status :: 3 - Alpha
Classifier: Intended Audience :: Developers
Classifier: License :: OSI Approved :: MIT License
Classifier: Programming Language :: Python :: 3
Classifier: Programming Language :: Python :: 3.8
Classifier: Programming Language :: Python :: 3.9
Classifier: Programming Language :: Python :: 3.10
Classifier: Programming Language :: Python :: 3.11
Classifier: Programming Language :: Python :: 3.12
Requires-Python: >=3.8
License-File: LICENSE
Dynamic: license-file
